pykanban/__init__.py
pykanban/auth.py
pykanban/config.py
pykanban/models.py
pykanban/routes.py
pykanban/web.db
pykanban/static/styles/form.css
pykanban/static/styles/header.css
pykanban/static/styles/index.css
pykanban/templates/_formhelpers.html
pykanban/templates/_header.html
pykanban/templates/_messages.html
pykanban/templates/home.html
pykanban/templates/index.html
pykanban/templates/login.html
pykanban/templates/new_password.html
pykanban/templates/reset.html
pykanban/templates/reset_password_email.html
pykanban/templates/signup.html
pykanban-0.1.0.dist-info/LICENSE
pykanban-0.1.0.dist-info/WHEEL
pykanban-0.1.0.dist-info/METADATA
pykanban-0.1.0.dist-info/RECORD
