Metadata-Version: 2.1
Name: pykanban
Version: 0.1.0
Summary: Initializing flask project 
Home-page: https://github.com/luccabb/flask_kanban
Author: Lucca Bertoncini
Author-email: luccabazzo@gmail.com
Classifier: License :: OSI Approved :: MIT License
